LICENSE
LICENSE.gluon-ts
README.md
setup.cfg
setup.py
transtimegrad/__init__.py
transtimegrad/util.py
transtimegrad.egg-info/PKG-INFO
transtimegrad.egg-info/SOURCES.txt
transtimegrad.egg-info/dependency_links.txt
transtimegrad.egg-info/requires.txt
transtimegrad.egg-info/top_level.txt
transtimegrad.egg-info/zip-safe
transtimegrad/dataset/__init__.py
transtimegrad/dataset/repository/__init__.py
transtimegrad/dataset/repository/_m5.py
transtimegrad/dataset/repository/datasets.py
transtimegrad/distributions/__init__.py
transtimegrad/distributions/utils.py
transtimegrad/distributions/zero_inflated.py
transtimegrad/feature/__init__.py
transtimegrad/feature/holiday.py
transtimegrad/model/__init__.py
transtimegrad/model/epsilon_theta.py
transtimegrad/model/rnn_timegrad/__init__.py
transtimegrad/model/rnn_timegrad/estimator.py
transtimegrad/model/rnn_timegrad/lightning_module.py
transtimegrad/model/rnn_timegrad/module.py
transtimegrad/model/trans_timegrad/__init__.py
transtimegrad/model/trans_timegrad/estimator.py
transtimegrad/model/trans_timegrad/lightning_module.py
transtimegrad/model/trans_timegrad/module.py
transtimegrad/model/transformer/__init__.py
transtimegrad/model/transformer/estimator.py
transtimegrad/model/transformer/lightning_module.py
transtimegrad/model/transformer/module.py
transtimegrad/modules/__init__.py
transtimegrad/modules/distribution_output.py
transtimegrad/modules/flows.py
transtimegrad/modules/gaussian_diffusion.py