Metadata-Version: 2.1
Name: transtimegrad
Version: 1.0
Summary: Transformer Based TimeGrad Model
Home-page: https://github.com/nbukhanchenko/transtimegrad
Author: Nikita Bukhanchenko
Author-email: nbukhanchenko@nes.ru
License: MIT
Requires-Python: >=3.8
License-File: LICENSE
License-File: LICENSE.gluon-ts
